compsci399_grpc/__init__.py
compsci399_grpc/user_pb2.py
compsci399_grpc/user_pb2_grpc.py
compsci399_grpc-1.0.11.dist-info/METADATA
compsci399_grpc-1.0.11.dist-info/WHEEL
compsci399_grpc-1.0.11.dist-info/top_level.txt
compsci399_grpc-1.0.11.dist-info/RECORD
