Metadata-Version: 2.4
Name: compsci399-grpc
Version: 1.0.11
Summary: Generated gRPC Python stubs for my service
Requires-Dist: grpcio>=1.44.0
Requires-Dist: protobuf>=3.19.0
Dynamic: requires-dist
Dynamic: summary
